.editorconfig
.gitignore
LICENSE
README.md
pyproject.toml
setup.py
.github/workflows/build.yaml
certbot_standalone_nfq/__init__.py
certbot_standalone_nfq/_version.py
certbot_standalone_nfq/auth.py
certbot_standalone_nfq.egg-info/PKG-INFO
certbot_standalone_nfq.egg-info/SOURCES.txt
certbot_standalone_nfq.egg-info/dependency_links.txt
certbot_standalone_nfq.egg-info/entry_points.txt
certbot_standalone_nfq.egg-info/requires.txt
certbot_standalone_nfq.egg-info/top_level.txt
snap/snapcraft.yaml