Metadata-Version: 2.1
Name: certbot-standalone-nfq
Version: 0.1.3
Summary: Certbot HTTP authenticator that works with any web server.
Author-email: Alex Zorin <alex@zorin.au>
License: GPL-2.0
Project-URL: repository, https://github.com/alexzorin/certbot-standalone-nfq
Requires-Python: >=3.7
License-File: LICENSE
Requires-Dist: scapy
Requires-Dist: pyroute2
Requires-Dist: fnfqueue
Requires-Dist: certbot>=1.25.0
Requires-Dist: acme>=1.25.0
